cesped/__init__.py
cesped/constants.py
cesped/evaluateEntry.py
cesped/inferEntry.py
cesped/particlesDataset.py
cesped/trainEntry.py
cesped/configs/defaultDataAugmentation.yaml
cesped/configs/defaultDataConfig.yaml
cesped/configs/defaultInferenceConfig.yaml
cesped/configs/defaultModelConfig.yaml
cesped/configs/defaultOptimizerConfig.yaml
cesped/configs/defaultRelionConfig.yaml
cesped/configs/defaultTrainerConfig.yaml
cesped/datamanager/__init__.py
cesped/datamanager/augmentations.py
cesped/datamanager/ctf.py
cesped/datamanager/plDataset.py
cesped/datamanager/relionStarDataset.py
cesped/network/__init__.py
cesped/network/featureExtractors.py
cesped/network/image2sphere.py
cesped/network/plModule.py
cesped/utils/__init__.py
cesped/utils/angles.py
cesped/utils/anglesStats.py
cesped/utils/cliBuilder.py
cesped/utils/fsc.py
cesped/utils/gaussianFilters.py
cesped/utils/tensors.py
cesped/utils/volumeStats.py
cesped/zenodo/__init__.py
cesped/zenodo/bechmarkUrls.py
cesped/zenodo/downloadFromZenodo.py
cesped/zenodo/tokens.py
cesped/zenodo/uploadToZenodo.py
tests/__init__.py
tests/test_anglesStats.py
tests/test_particlesDataset.py
cesped-24.7.0.dist-info/LICENSE
cesped-24.7.0.dist-info/METADATA
cesped-24.7.0.dist-info/WHEEL
cesped-24.7.0.dist-info/top_level.txt
cesped-24.7.0.dist-info/RECORD
