Metadata-Version: 2.1
Name: cesped
Version: 24.7.0
Summary: Code utilities for the CESPED (Cryo-EM Supervised Pose Estimation Dataset) benchmark
Home-page: https://github.com/rsanchezgarc/cesped
Author: Ruben Sanchez-Garcia
Author-email: ruben.sanchez-garcia@stats.ox.ac.uk
Keywords: deep learning cryoem pose estimation
License-File: LICENSE
Requires-Dist: argParseFromDoc >=0.1.2
Requires-Dist: einops >=0.8.0
Requires-Dist: e3nn >=0.5.1
Requires-Dist: healpy >=1.16.5
Requires-Dist: joblib >=1.3
Requires-Dist: mrcfile <2.0.0,>=1.4.3
Requires-Dist: numpy >=1.25.2
Requires-Dist: omegaconf >=2.3.0
Requires-Dist: pandas >=2.1.0
Requires-Dist: pdoc3 >=0.10.0
Requires-Dist: psutil >=5.9.5
Requires-Dist: lightning[pytorch-extra] <3.0.0,>=2.0.0
Requires-Dist: requests >=2.31.0
Requires-Dist: scipy >=1.11.2
Requires-Dist: starfile >=0.4.12
Requires-Dist: starstack >=0.2.0
Requires-Dist: tensorboard >=2.12.1
Requires-Dist: torch <3.0.0,>=2.0.0
Requires-Dist: torchvision >=0.15.2
